{
  "slug": "cure",
  "title": "Cure",
  "menuItalic": true,
  "subtitle": "Cure Beauty",
  "link": {
    "label": "curenails.co",
    "url": "https://curenails.co/"
  },
  "awwwards": "Site of the day, Mobile excellence, Devaward",
  "type": "Boutique promo website",
  "skills": ["Art Direction","Content creation","Branding","Interface Design","Interaction Design"],
  "intro": "Unique nail and wax boutique that curated a build-your-own style menu.",
  "header": [
    "Cure is a unique nail and wax boutique.",
    "It’is curated a build-your-own style menu by creating its own natural and organic skincare products that are used in services.",
    "Cure was founded in 2018 in El Paso, Texas. At Cure we focus on customer experience, health and happiness."
  ],
  "cover": "cure/cure.jpg",
  "homeMenu": "cure/cure-home.jpg",
  "content": [
    {
      "type": "vImageBackground",
      "url": "cure/cure-1.jpg",
      "alt": "Cure Beauty"
    },
    {
      "type": "vImage",
      "width": 22,
      "background": "#E5DEDE",
      "url": "cure/cure-2.jpg",
      "alt": "Cure Beauty"
    },
    {
      "type": "vText",
      "header": "Great news! <br> We've got Site of the day on Awwwards for this website!",
      "paragraphs": [
        "Cure’s goal is to provide El Paso a different type of nail & wax experience that I was aimed at demonstrating via the website, branding and content created. "
      ]
    },
    {
      "type": "vImage",
      "width": 70,
      "url": "cure/cure-3.jpg",
      "alt": "Cure Beauty"
    },
    {
      "type": "vImageBackground",
      "url": "cure/cure-4.jpg",
      "alt": "Cure Beauty"
    },
    {
      "type": "vImageText",
      "url": "cure/cure-5.jpg",
      "alt": "Cure Beauty",
      "header": "The website also received Honorable Mention, Mobile Excellence and Development awards.",
      "paragraphs": [
        "From logo creation to website design and animation, this project was so much fan to work on. I also had a chance to organize and lead the photo shoot to ensure the website and promo materials are leveraging unique visual content."
      ]
    },
    {
      "type": "vImage",
      "width": 70,
      "url": "cure/cure-6.jpg",
      "alt": "Cure Beauty"
    },
    {
      "type": "vImage",
      "width": 70,
      "url": "cure/cure-7.jpg",
      "alt": "Cure Beauty"
    },
    {
      "type": "vImage",
      "width": 40,
      "background": "#6E787D",
      "top": "60",
      "shadow": "cure/shadow-cure.png",
      "url": "cure/cure-8.jpg",
      "alt": "Cure Beauty"
    },
    {
      "type": "vImage",
      "width": 40,
      "background": "#6E787D",
      "shadow": "cure/shadow-cure.png",
      "top": "40",
      "url": "cure/cure-9.jpg",
      "alt": "Cure Beauty"
    },
    {
      "type": "vImages",
      "images":[
        {
          "url": "cure/cure-10.jpg",
          "alt": "Cure Beauty"
        },
        {
          "url": "cure/cure-11.jpg",
          "alt": "Cure Beauty"
        }
      ]
    },
    {
      "type": "vImage",
      "width": 22,
      "url": "cure/cure-12.jpg",
      "alt": "Cure Beauty"
    },
    {
      "type": "vImageBackground",
      "url": "cure/cure-13.jpg",
      "alt": "Cure Beauty"
    }
  ]
}
